twitter_dm/__init__.py
twitter_dm/libcpr.1.11.1.dylib
twitter_dm/libcpr.1.dylib
twitter_dm/libcpr.dylib
twitter_dm/libcpr.so
twitter_dm/libcurl.4.8.0.dylib
twitter_dm/libcurl.4.dylib
twitter_dm/libcurl.dylib
twitter_dm/libcurl.so
twitter_dm/libz.1.2.13.zlib-ng.dylib
twitter_dm/libz.1.dylib
twitter_dm/libz.dylib
twitter_dm/libz.so
twitter_dm/metadata.py
twitter_dm/twitter_dm.cpython-312-darwin.so
twitter_dm/twitter_dm.cpython-312-x86_64-linux-gnu.so
twitter_dm_static-0.1.4.dist-info/METADATA
twitter_dm_static-0.1.4.dist-info/WHEEL
twitter_dm_static-0.1.4.dist-info/top_level.txt
twitter_dm_static-0.1.4.dist-info/RECORD
