Metadata-Version: 2.4
Name: twitter-dm-static
Version: 0.1.4
Summary: Twitter DM static analysis tool with C++ backend
Home-page: https://github.com/yourusername/twitter-dm-static
Author: robin
Author-email: robin <robin528919@gmail.com>
Project-URL: Homepage, https://github.com/yourusername/twitter-dm-static
Project-URL: Repository, https://github.com/yourusername/twitter-dm-static.git
Project-URL: Issues, https://github.com/yourusername/twitter-dm-static/issues
Classifier: Development Status :: 3 - Alpha
Classifier: Intended Audience :: Developers
Classifier: License :: OSI Approved :: MIT License
Classifier: Programming Language :: Python :: 3
Classifier: Programming Language :: Python :: 3.8
Classifier: Programming Language :: Python :: 3.9
Classifier: Programming Language :: Python :: 3.10
Classifier: Programming Language :: Python :: 3.11
Classifier: Programming Language :: Python :: 3.12
Classifier: Programming Language :: C++
Requires-Python: >=3.8
Provides-Extra: dev
Requires-Dist: pytest>=6.0; extra == "dev"
Requires-Dist: pytest-cov; extra == "dev"
Requires-Dist: black; extra == "dev"
Requires-Dist: flake8; extra == "dev"
Dynamic: author
Dynamic: home-page
Dynamic: requires-python
